jigutime/__init__.py
jigutime/jigu.py
jigutime-0.2.1.dist-info/METADATA
jigutime-0.2.1.dist-info/WHEEL
jigutime-0.2.1.dist-info/entry_points.txt
jigutime-0.2.1.dist-info/top_level.txt
jigutime-0.2.1.dist-info/RECORD
