Metadata-Version: 2.1
Name: jigutime
Version: 0.2.1
Summary: Default template for PDM package
Author-email: Nicou11 <lyoungin1204@gmail.com>
License: MIT
Requires-Python: >=3.9
Requires-Dist: pytz>=2024.2
